<?xml version="1.0" encoding="iso-8859-1"?>
<bilhetes>
  <nr_arquivo>24757807</nr_arquivo>
  <data_geracao>01/10/2025</data_geracao>
  <hora_geracao>14:55</hora_geracao>
  <nome_agencia>uniglobe pro</nome_agencia>
  <versao_xml>4</versao_xml>
  <bilhete>
    <idv_externo>13203</idv_externo>
    <data_lancamento>11/07/2025</data_lancamento>
    <codigo_produto>tkt</codigo_produto>
    <fornecedor>la</fornecedor>
    <num_bilhete>2971298704</num_bilhete>
    <prestador_svc>la</prestador_svc>
    <forma_de_pagamento>cc</forma_de_pagamento>
    <moeda>brl</moeda>
    <emissor>TMS</emissor>
    <cliente>1 ODONTOPREV S A</cliente>
    <ccustos_cliente>201007 - CONTROLADORIA - ADMINISTRATIVO FINANCEIRO (CONTABILIDADE, CONTROLADORIA, RI)</ccustos_cliente>
    <solicitante>DIEGO SANTANA</solicitante>
    <aprovador>ANDRESSA CARDOSO DA SILVA</aprovador>
    <departamento>SUPERINTENDÊNCIA DE CONTROLADORIA</departamento>
    <motivo_viagem>DESENVOLVIMENTO DE NEGOCIOS</motivo_viagem>
    <motivo_recusa>POR PRECO</motivo_recusa>
    <matricula>106808</matricula>
    <numero_requisicao>13203</numero_requisicao>
    <localizador>HIUOQZ</localizador>
    <passageiro>DIEGO SANTANA</passageiro>
    <tipo_domest_inter>d</tipo_domest_inter>
    <tipo_roteiro>1</tipo_roteiro>
    <valores>
      <item>
        <codigo>tarifa</codigo>
        <valor>1877.27</valor>
      </item>
      <item>
        <codigo>taxa</codigo>
        <valor>114.19</valor>
      </item>
      <item>
        <codigo>taxa_du</codigo>
        <valor>0.00</valor>
      </item>
    </valores>
    <roteiro>
      <aereo>
        <trecho>
          <cia_iata>la</cia_iata>
          <numero_voo>-</numero_voo>
          <aeroporto_origem>CGH</aeroporto_origem>
          <aeroporto_destino>FOR</aeroporto_destino>
          <data_partida>31/07/2025</data_partida>
          <classe>G/Q</classe>
        </trecho>
        <trecho>
          <cia_iata>la</cia_iata>
          <numero_voo>-</numero_voo>
          <aeroporto_origem>FOR</aeroporto_origem>
          <aeroporto_destino>CGH</aeroporto_destino>
          <data_partida>31/07/2025</data_partida>
          <classe>G/Q</classe>
        </trecho>
      </aereo>
    </roteiro>
    <info_adicionais>HORARIO DE CHEGADA DO VOO NO DESTINO NAO ATENDE NECESSIDADE</info_adicionais>
  </bilhete>
</bilhetes>